app4_sdk/__init__.py
app4_sdk/plugin/__init__.py
app4_sdk/plugin/context.py
app4_sdk/plugin/export.py
app4_sdk/plugin/helpers.py
app4_sdk/plugin/plugin.py
app4_sdk/plugin/registry.py
app4_sdk/plugin/server.py
app4_sdk/plugin/types.py
app4_sdk/proto/__init__.py
app4_sdk/proto/plugin.proto
app4_sdk/proto/plugin_pb2.py
app4_sdk/proto/plugin_pb2.pyi
app4_sdk/proto/plugin_pb2_grpc.py
app4_sdk/proto/registry.proto
app4_sdk/proto/registry_pb2.py
app4_sdk/proto/registry_pb2.pyi
app4_sdk/proto/registry_pb2_grpc.py
app4_sdk-1.1.0.dist-info/METADATA
app4_sdk-1.1.0.dist-info/WHEEL
app4_sdk-1.1.0.dist-info/top_level.txt
app4_sdk-1.1.0.dist-info/RECORD
