Metadata-Version: 2.4
Name: app4-sdk
Version: 1.1.0
Summary: Python SDK for building App4 plugins
Author-email: App4 Team <team@app4.ai>
License: MIT
Project-URL: Homepage, https://github.com/app4ai/app4-plugin-sdk
Project-URL: Documentation, https://docs.app4.ai/sdk/python
Project-URL: Repository, https://github.com/app4ai/app4-plugin-sdk
Project-URL: Issues, https://github.com/app4ai/app4-plugin-sdk/issues
Keywords: app4,plugin,grpc,sdk
Classifier: Development Status :: 4 - Beta
Classifier: Intended Audience :: Developers
Classifier: License :: OSI Approved :: MIT License
Classifier: Operating System :: OS Independent
Classifier: Programming Language :: Python :: 3
Classifier: Programming Language :: Python :: 3.10
Classifier: Programming Language :: Python :: 3.11
Classifier: Programming Language :: Python :: 3.12
Classifier: Topic :: Software Development :: Libraries :: Python Modules
Requires-Python: >=3.10
Requires-Dist: grpcio>=1.60.0
Requires-Dist: protobuf>=4.25.0
Provides-Extra: dev
Requires-Dist: grpcio-tools>=1.60.0; extra == "dev"
Requires-Dist: pytest>=7.0.0; extra == "dev"
Requires-Dist: pytest-asyncio>=0.21.0; extra == "dev"
Requires-Dist: mypy>=1.0.0; extra == "dev"
Requires-Dist: black>=23.0.0; extra == "dev"
Requires-Dist: isort>=5.12.0; extra == "dev"
Requires-Dist: ruff>=0.1.0; extra == "dev"
